MANIFEST.in
setup.py
fluff/__init__.py
fluff/exceptions.py
fluff/filters.py
fluff/models.py
fluff/signals.py
fluff/sync_couchdb.py
fluff/util.py
fluff/_design/views/generic/map.js
fluff/_design/views/generic/reduce.js
fluff/fluff_filter/__init__.py
fluff/fluff_filter/models.py
fluff/fluff_filter/_design/filters/domain_type.js
pillowfluff.egg-info/PKG-INFO
pillowfluff.egg-info/SOURCES.txt
pillowfluff.egg-info/dependency_links.txt
pillowfluff.egg-info/requires.txt
pillowfluff.egg-info/top_level.txt