Metadata-Version: 1.0
Name: pillowfluff
Version: 0.0.4
Summary: Map over CouchDB changes feed built to run on Pillowtop
Home-page: http://www.dimagi.com/
Author: Dimagi
Author-email: information@dimagi.com
License: UNKNOWN
Platform: UNKNOWN
